realbook/__init__.py
realbook/callbacks/__init__.py
realbook/callbacks/debugging.py
realbook/callbacks/spectrogram_visualization.py
realbook/callbacks/speed.py
realbook/callbacks/utilization.py
realbook/layers/__init__.py
realbook/layers/compatibility.py
realbook/layers/math.py
realbook/layers/nnaudio.py
realbook/layers/signal.py
realbook/vendor/__init__.py
realbook/vendor/librosa_filters.py
tests/__init__.py
tests/callbacks/test_debugging.py
tests/callbacks/test_spectrogram_visualization.py
tests/callbacks/test_speed.py
tests/callbacks/test_utilization.py
tests/layers/create_model_with_control_inputs.py
tests/layers/test_compatibility.py
tests/layers/test_math.py
tests/layers/test_nnaudio.py
tests/layers/test_signal.py
realbook-1.0.3.dist-info/LICENSE
realbook-1.0.3.dist-info/METADATA
realbook-1.0.3.dist-info/NOTICE
realbook-1.0.3.dist-info/WHEEL
realbook-1.0.3.dist-info/top_level.txt
realbook-1.0.3.dist-info/RECORD
